drt/__init__.py
drt/configfile.py
drt/drt.py
drt/drtp.py
drt/dvddisc.py
drt/dvdinfo.py
drt/dvdprocess.py
drt/dvdtrack.py
drt/filesystem.py
drt/saveddvd.py
drt-1.2.1.dist-info/LICENSE
drt-1.2.1.dist-info/METADATA
drt-1.2.1.dist-info/WHEEL
drt-1.2.1.dist-info/entry_points.txt
drt-1.2.1.dist-info/top_level.txt
drt-1.2.1.dist-info/RECORD
