Metadata-Version: 2.1
Name: drt
Version: 1.2.1
Summary: dvd copying and ripping management tool
Home-page: https://github.com/ccdale/drt
Author: Christopher Allison
Author-email: chris.charles.allison+drt@gmail.com
License: UNKNOWN
Project-URL: Source, https://github.com/ccdale/drt
Project-URL: Bug Reports, https://github.com/ccdale/drt/issues
Keywords: dvd copying ripping conversion
Platform: UNKNOWN
Classifier: Development Status :: 4 - Beta
Classifier: Environment :: Console
Classifier: Intended Audience :: End Users/Desktop
Classifier: License :: OSI Approved :: GNU General Public License v3 or later (GPLv3+)
Classifier: Natural Language :: English
Classifier: Operating System :: POSIX :: Linux
Classifier: Programming Language :: Python :: 3
Classifier: Topic :: Multimedia :: Video :: Conversion
Classifier: Topic :: System :: Archiving
Classifier: Topic :: System :: Archiving :: Backup
Classifier: Topic :: System :: Archiving :: Compression
Classifier: Topic :: System :: Archiving :: Mirroring
Classifier: Topic :: Utilities
Requires-Python: >=3
Requires-Dist: docopt
